README.md
README.rst
setup.py
yfjpscraper/__init__.py
yfjpscraper/parser.py
yfjpscraper.egg-info/PKG-INFO
yfjpscraper.egg-info/SOURCES.txt
yfjpscraper.egg-info/dependency_links.txt
yfjpscraper.egg-info/requires.txt
yfjpscraper.egg-info/top_level.txt