Metadata-Version: 2.1
Name: yfjpscraper
Version: 0.5.1
Summary: yahoo finance japan parser
Home-page: https://github.com/fx-kirin/yfjpscraper
Author: fx-kirin
Author-email: fx.kirin@gmail.com
